functions.py
cmi_biosignal_lib-0.0.2.dist-info/METADATA
cmi_biosignal_lib-0.0.2.dist-info/WHEEL
cmi_biosignal_lib-0.0.2.dist-info/top_level.txt
cmi_biosignal_lib-0.0.2.dist-info/RECORD
